agesafetch-2.0.2.dist-info/METADATA
agesafetch-2.0.2.dist-info/WHEEL
agesafetch-2.0.2.dist-info/entry_points.txt
agesafetch-2.0.2.dist-info/licenses/LICENSE
agesafetch/__init__.py
agesafetch/__init__.pyi
agesafetch/agesafetch.cpython-311-x86_64-linux-gnu.so
agesafetch/py.typed
agesafetch-2.0.2.dist-info/RECORD
