Metadata-Version: 2.4
Name: agesafetch
Version: 2.0.2
Classifier: Development Status :: 5 - Production/Stable
Classifier: Environment :: Console
Classifier: Intended Audience :: End Users/Desktop
Classifier: Intended Audience :: System Administrators
Classifier: Natural Language :: English
Classifier: Operating System :: POSIX :: Linux
Classifier: Programming Language :: Python :: 3.10
Classifier: Programming Language :: Python :: 3.11
Classifier: Programming Language :: Python :: 3.12
Classifier: Programming Language :: Python :: 3.13
Classifier: Programming Language :: Rust
Classifier: Topic :: System :: Hardware
Classifier: Topic :: System :: Monitoring
Classifier: Topic :: Utilities
Classifier: Typing :: Typed
License-File: LICENSE
Summary: A tool for obtaining your firmware's embedded AGESA version on Linux.
Keywords: agesa,amd,firmware,memory,uefi
Author: Benedikt Vollmerhaus <benedikt@vollmerhaus.org>
Author-email: Benedikt Vollmerhaus <benedikt@vollmerhaus.org>
License-Expression: MIT
Requires-Python: >=3.10
Project-URL: Repository, https://gitlab.com/BVollmerhaus/agesafetch
Project-URL: Changelog, https://gitlab.com/BVollmerhaus/agesafetch/-/blob/master/CHANGELOG.md
Project-URL: Issues, https://gitlab.com/BVollmerhaus/agesafetch/-/issues
